setup.py
beauty_view/__init__.py
beauty_view/auth.py
beauty_view/post.py
django_beauty_view.egg-info/PKG-INFO
django_beauty_view.egg-info/SOURCES.txt
django_beauty_view.egg-info/dependency_links.txt
django_beauty_view.egg-info/requires.txt
django_beauty_view.egg-info/top_level.txt