Metadata-Version: 1.1
Name: django-beauty-view
Version: 0.0.5
Summary: Beauty Django Views Mixin
Home-page: https://bitbucket.org/voronkovd/django-beauty-view
Author: Dmitry Voronkov
Author-email: mail@voronkovd.ru
License: GNU General Public License
Platform: UNKNOWN
Classifier: Development Status :: 3 - Alpha
Classifier: Intended Audience :: Developers
Classifier: Intended Audience :: Science/Research
Classifier: License :: OSI Approved :: GNU General Public License (GPL)
Classifier: Natural Language :: Russian
Classifier: Programming Language :: Python
Classifier: Programming Language :: Python :: 2.7
Classifier: Programming Language :: Python :: 3
Classifier: Programming Language :: Python :: 3.2
Classifier: Programming Language :: Python :: 3.3
Classifier: Programming Language :: Python :: 3.4
Classifier: Topic :: Software Development :: Libraries :: Python Modules
